turtles/__init__.py
turtles/dsl.py
turtles/dsl.pyi
turtles/gll.py
turtles/grammar.py
turtles/examples/__init__.py
turtles/examples/csv.py
turtles/examples/html.py
turtles/examples/json.py
turtles/examples/json_toy.py
turtles/examples/md.py
turtles/examples/semver.py
turtles/examples/yaml.py
turtles/legacy/__init__.py
turtles-2.0.6.dist-info/METADATA
turtles-2.0.6.dist-info/WHEEL
turtles-2.0.6.dist-info/licenses/LICENSE
turtles-2.0.6.dist-info/RECORD
