Metadata-Version: 2.4
Name: turtles
Version: 2.0.6
Summary: Simple python DSL for parsing text
Project-URL: repository, https://github.com/david-andrew/turtles
Author-email: David Samson <david.andrew.engineer@gmail.com>
License: MIT License
License-File: LICENSE
Classifier: License :: OSI Approved :: MIT License
Classifier: Programming Language :: Python :: 3
Classifier: Programming Language :: Python :: 3.12
Classifier: Programming Language :: Python :: 3.13
Classifier: Programming Language :: Python :: 3.14
Requires-Python: >=3.12
Requires-Dist: prettyerr>=0.0.3
